datasette_sqlite_lembed/__init__.py
datasette_sqlite_lembed-0.0.1a8.dist-info/METADATA
datasette_sqlite_lembed-0.0.1a8.dist-info/WHEEL
datasette_sqlite_lembed-0.0.1a8.dist-info/entry_points.txt
datasette_sqlite_lembed-0.0.1a8.dist-info/top_level.txt
datasette_sqlite_lembed-0.0.1a8.dist-info/RECORD
